fileorganize/__init__.py
fileorganize/utils.py
fileorganize-0.0.4.dist-info/licenses/LICENSE
fileorganize-0.0.4.dist-info/METADATA
fileorganize-0.0.4.dist-info/WHEEL
fileorganize-0.0.4.dist-info/top_level.txt
fileorganize-0.0.4.dist-info/RECORD
