Metadata-Version: 2.4
Name: fileorganize
Version: 0.0.4
Summary: Utility functions for corpus and experiment file management in Python
Author-email: Keith Johnson <kjohnson@berkeley.edu>, Ronald Sprouse <ronald@berkeley.edu>
License-Expression: BSD-3-Clause
Project-URL: Homepage, https://github.com/phonetics-projects/file-organization
Project-URL: Issues, https://github.com/phonetics-projects/file-organization/issues
Classifier: Programming Language :: Python :: 3
Classifier: Operating System :: OS Independent
Classifier: Intended Audience :: Science/Research
Classifier: Topic :: Scientific/Engineering
Requires-Python: >=3.0
License-File: LICENSE
Requires-Dist: pandas
Dynamic: license-file
